ukrdc_xsdata/__init__.py
ukrdc_xsdata/pv/__init__.py
ukrdc_xsdata/pv/pv_2_0.py
ukrdc_xsdata/rrtf/__init__.py
ukrdc_xsdata/rrtf/rrtf_4.py
ukrdc_xsdata/ukrdc/__init__.py
ukrdc_xsdata/ukrdc/patient.py
ukrdc_xsdata/ukrdc/ukrdc.py
ukrdc_xsdata/ukrdc/allergies/__init__.py
ukrdc_xsdata/ukrdc/allergies/allergy.py
ukrdc_xsdata/ukrdc/assessments/__init__.py
ukrdc_xsdata/ukrdc/assessments/assessment.py
ukrdc_xsdata/ukrdc/clinical_relationships/__init__.py
ukrdc_xsdata/ukrdc/clinical_relationships/clinical_relationship.py
ukrdc_xsdata/ukrdc/diagnoses/__init__.py
ukrdc_xsdata/ukrdc/diagnoses/cause_of_death.py
ukrdc_xsdata/ukrdc/diagnoses/diagnosis.py
ukrdc_xsdata/ukrdc/diagnoses/renal_diagnosis.py
ukrdc_xsdata/ukrdc/dialysis_prescriptions/__init__.py
ukrdc_xsdata/ukrdc/dialysis_prescriptions/dialysis_prescription.py
ukrdc_xsdata/ukrdc/dialysis_sessions/__init__.py
ukrdc_xsdata/ukrdc/dialysis_sessions/dialysis_session.py
ukrdc_xsdata/ukrdc/documents/__init__.py
ukrdc_xsdata/ukrdc/documents/document.py
ukrdc_xsdata/ukrdc/encounters/__init__.py
ukrdc_xsdata/ukrdc/encounters/encounter.py
ukrdc_xsdata/ukrdc/encounters/transplant_list.py
ukrdc_xsdata/ukrdc/encounters/treatment.py
ukrdc_xsdata/ukrdc/family_histories/__init__.py
ukrdc_xsdata/ukrdc/family_histories/family_history.py
ukrdc_xsdata/ukrdc/lab_orders/__init__.py
ukrdc_xsdata/ukrdc/lab_orders/lab_order.py
ukrdc_xsdata/ukrdc/medications/__init__.py
ukrdc_xsdata/ukrdc/medications/medication.py
ukrdc_xsdata/ukrdc/observations/__init__.py
ukrdc_xsdata/ukrdc/observations/observation.py
ukrdc_xsdata/ukrdc/opt_outs/__init__.py
ukrdc_xsdata/ukrdc/opt_outs/opt_out.py
ukrdc_xsdata/ukrdc/procedures/__init__.py
ukrdc_xsdata/ukrdc/procedures/procedure.py
ukrdc_xsdata/ukrdc/program_memberships/__init__.py
ukrdc_xsdata/ukrdc/program_memberships/program_membership.py
ukrdc_xsdata/ukrdc/social_histories/__init__.py
ukrdc_xsdata/ukrdc/social_histories/social_history.py
ukrdc_xsdata/ukrdc/surveys/__init__.py
ukrdc_xsdata/ukrdc/surveys/survey.py
ukrdc_xsdata-4.2.0.dist-info/METADATA
ukrdc_xsdata-4.2.0.dist-info/WHEEL
ukrdc_xsdata-4.2.0.dist-info/top_level.txt
ukrdc_xsdata-4.2.0.dist-info/RECORD
