Metadata-Version: 2.1
Name: ukrdc-xsdata
Version: 4.2.0
Summary: UNKNOWN
Home-page: https://www.renalreg.org/
Author: UK Renal Registry
Author-email: rrsystems@renalregistry.nhs.uk
License: UNKNOWN
Platform: UNKNOWN
Requires-Dist: xsdata
